odoo/addons/purchase_line_service_qty_received/README.rst
odoo/addons/purchase_line_service_qty_received/__init__.py
odoo/addons/purchase_line_service_qty_received/__manifest__.py
odoo/addons/purchase_line_service_qty_received/i18n/it.po
odoo/addons/purchase_line_service_qty_received/i18n/purchase_line_service_qty_received.pot
odoo/addons/purchase_line_service_qty_received/models/__init__.py
odoo/addons/purchase_line_service_qty_received/models/purchase_order_line.py
odoo/addons/purchase_line_service_qty_received/readme/CONTRIBUTORS.rst
odoo/addons/purchase_line_service_qty_received/readme/DESCRIPTION.rst
odoo/addons/purchase_line_service_qty_received/static/description/icon.png
odoo/addons/purchase_line_service_qty_received/static/description/index.html
odoo/addons/purchase_line_service_qty_received/tests/__init__.py
odoo/addons/purchase_line_service_qty_received/tests/common.py
odoo/addons/purchase_line_service_qty_received/tests/test_service_line_qty_received.py
odoo14_addon_purchase_line_service_qty_received-14.0.1.0.1.dev3.dist-info/METADATA
odoo14_addon_purchase_line_service_qty_received-14.0.1.0.1.dev3.dist-info/WHEEL
odoo14_addon_purchase_line_service_qty_received-14.0.1.0.1.dev3.dist-info/top_level.txt
odoo14_addon_purchase_line_service_qty_received-14.0.1.0.1.dev3.dist-info/RECORD
