Metadata-Version: 2.1
Name: odoo14-addon-purchase_line_service_qty_received
Version: 14.0.1.0.1.dev3
Summary: Changes the Received Quantity (qty_received) of a service purchase.order.lineif one other purchase.order.line is received the qty_received of the service lineis changed to its Quantity (product_uom_qty)
Home-page: https://github.com/OCA/purchase-workflow
Author: Raumschmiede GmbH, MT Software, Odoo Community Association (OCA)
Author-email: support@odoo-community.org
License: LGPL-3
Classifier: Programming Language :: Python
Classifier: Framework :: Odoo
Classifier: Framework :: Odoo :: 14.0
Classifier: License :: OSI Approved :: GNU Lesser General Public License v3 (LGPLv3)
Requires-Python: >=3.6
Requires-Dist: odoo<14.1dev,>=14.0a
